webplus/cli.py
webplus-1.0.dist-info/METADATA
webplus-1.0.dist-info/WHEEL
webplus-1.0.dist-info/entry_points.txt
webplus-1.0.dist-info/top_level.txt
webplus-1.0.dist-info/RECORD
