Metadata-Version: 2.1
Name: webplus
Version: 1.0
Summary: CLI tool for the python WebPlus Framework
Home-page: UNKNOWN
Author: Tejas Nayak
Author-email: tejasnayak25@outlook.com
License: UNKNOWN
Platform: UNKNOWN
